setup.py
OS_Platform/OS_Platform.py
OS_Platform.egg-info/PKG-INFO
OS_Platform.egg-info/SOURCES.txt
OS_Platform.egg-info/dependency_links.txt
OS_Platform.egg-info/entry_points.txt
OS_Platform.egg-info/top_level.txt